mia/__init__.py
mia/estimators.py
mia/serialization.py
mia/wrappers.py
mia-0.1.2.dist-info/DESCRIPTION.rst
mia-0.1.2.dist-info/METADATA
mia-0.1.2.dist-info/RECORD
mia-0.1.2.dist-info/WHEEL
mia-0.1.2.dist-info/metadata.json
mia-0.1.2.dist-info/top_level.txt
