Metadata-Version: 2.0
Name: mia
Version: 0.1.2
Summary: A library for running membership inference attacks against ML models
Home-page: https://github.com/spring-epfl/mia
Author: Bogdan Kulynych, Mohammad Yaghini
Author-email: hello@bogdankulynych.me, mohammad.yaghini@epfl.ch
License: MIT
Platform: UNKNOWN
Classifier: Development Status :: 3 - Alpha
Classifier: Intended Audience :: Developers
Classifier: Natural Language :: English
Classifier: Operating System :: OS Independent
Classifier: Programming Language :: Python
Classifier: Programming Language :: Python :: 3
Classifier: Programming Language :: Python :: 3.4
Classifier: Programming Language :: Python :: 3.5
Classifier: Programming Language :: Python :: 3.6
Classifier: Programming Language :: Python :: Implementation :: CPython
Classifier: Topic :: Software Development :: Libraries :: Python Modules
Classifier: Topic :: Scientific/Engineering :: Artificial Intelligence
Classifier: License :: OSI Approved :: MIT License
Requires-Dist: numpy
Requires-Dist: scipy
Requires-Dist: scikit-learn
Requires-Dist: torch
Requires-Dist: tqdm
Provides-Extra: dev
Requires-Dist: pytest; extra == 'dev'
Requires-Dist: pytest-lazy-fixture; extra == 'dev'
Requires-Dist: tensorflow; extra == 'dev'
Requires-Dist: skorch; extra == 'dev'
Requires-Dist: keras; extra == 'dev'
Requires-Dist: sphinx; extra == 'dev'
Requires-Dist: sphinx-rtd-theme; extra == 'dev'
Requires-Dist: black; extra == 'dev'
Provides-Extra: test
Requires-Dist: pytest; extra == 'test'
Requires-Dist: pytest-lazy-fixture; extra == 'test'
Requires-Dist: tensorflow; extra == 'test'
Requires-Dist: skorch; extra == 'test'
Requires-Dist: keras; extra == 'test'
